{"startTime":1637455270499,"endTime":1637454153745,"scores":[{"id":"STEAM_0:0:21651069","name":"chINA #1 | maaarrk","team":"CT","kills":18,"deaths":10,"teamkills":0,"knifekills":0,"knifed":0,"suicides":0,"sips":63,"rounds":17,"active":true},{"id":"STEAM_0:0:32762533","name":"Fårikål | jÆBBØH","team":"TERRORIST","kills":17,"deaths":12,"teamkills":0,"knifekills":0,"knifed":0,"suicides":0,"sips":63,"rounds":17,"active":true},{"id":"STEAM_0:1:11611559","name":"Fælles Kålkontrol | alstrup","team":"TERRORIST","kills":10,"deaths":12,"teamkills":0,"knifekills":1,"knifed":1,"suicides":1,"sips":58,"rounds":17,"active":true},{"id":"STEAM_0:0:13961031","name":"Big Drink | Mikkel","team":"CT","kills":14,"deaths":9,"teamkills":0,"knifekills":1,"knifed":1,"suicides":0,"sips":54,"rounds":17,"active":true},{"id":"STEAM_0:0:161232090","name":"VOLD, KONTROL, SKABER | >:( CAR","team":"TERRORIST","kills":2,"deaths":15,"teamkills":0,"knifekills":0,"knifed":0,"suicides":0,"sips":36,"rounds":17,"active":true},{"id":"STEAM_0:0:1936508","name":"Heinz","team":"CT","kills":4,"deaths":10,"teamkills":0,"knifekills":0,"knifed":0,"suicides":0,"sips":35,"rounds":17,"active":true},{"id":"STEAM_0:1:34134896","name":"hvad er virleightged? | eMIL","team":"CT","kills":2,"deaths":0,"teamkills":0,"knifekills":0,"knifed":0,"suicides":0,"sips":7,"rounds":3,"active":true},{"id":"STEAM_0:1:14846448","name":"---___--- i Thue","team":"UNASSIGNED","kills":0,"deaths":0,"teamkills":0,"knifekills":0,"knifed":0,"suicides":0,"sips":0,"rounds":0,"active":false}]}