{"startTime":1660252181082,"scores":[{"id":"STEAM_0:1:12769831","name":"Lasse ikke Alstrup","team":"TERRORIST","kills":26,"deaths":6,"teamkills":0,"knifekills":1,"knifed":0,"suicides":0,"sips":73,"rounds":15,"active":true},{"id":"STEAM_0:1:11318024","name":"GÆT HVIS RØV | Bob","team":"TERRORIST","kills":18,"deaths":6,"teamkills":1,"knifekills":1,"knifed":0,"suicides":0,"sips":72,"rounds":15,"active":true},{"id":"STEAM_0:1:11611559","name":"Bananconnoisseur Alstrup","team":"CT","kills":23,"deaths":7,"teamkills":0,"knifekills":0,"knifed":1,"suicides":0,"sips":68,"rounds":15,"active":true},{"id":"STEAM_0:0:29158958","name":"lasse har en skæv fisse|'Bernt","team":"CT","kills":11,"deaths":12,"teamkills":0,"knifekills":0,"knifed":1,"suicides":0,"sips":49,"rounds":15,"active":true},{"id":"STEAM_0:1:39235412","name":"Epic Big Sex| chris","team":"CT","kills":8,"deaths":13,"teamkills":0,"knifekills":1,"knifed":0,"suicides":0,"sips":44,"rounds":15,"active":true},{"id":"STEAM_0:0:161232090","name":"Lets have shrex | CARO","team":"TERRORIST","kills":8,"deaths":12,"teamkills":0,"knifekills":0,"knifed":1,"suicides":0,"sips":43,"rounds":15,"active":true},{"id":"STEAM_0:0:13961031","name":"Big Drink | Mikkel","team":"CT","kills":7,"deaths":11,"teamkills":0,"knifekills":1,"knifed":0,"suicides":0,"sips":39,"rounds":14,"active":true},{"id":"STEAM_0:0:1936508","name":"Heinz","team":"CT","kills":6,"deaths":10,"teamkills":0,"knifekills":0,"knifed":0,"suicides":0,"sips":37,"rounds":15,"active":true},{"id":"STEAM_0:1:78911275","name":"Big Boobs - Pattie","team":"TERRORIST","kills":5,"deaths":11,"teamkills":0,"knifekills":0,"knifed":1,"suicides":0,"sips":36,"rounds":15,"active":true},{"id":"STEAM_0:1:156056572","name":"stonks | mai","team":"TERRORIST","kills":2,"deaths":13,"teamkills":0,"knifekills":0,"knifed":0,"suicides":0,"sips":32,"rounds":15,"active":true},{"id":"STEAM_0:1:575443358","name":"IKKE KNIFE MIG |JEAMEPPE","team":"CT","kills":2,"deaths":12,"teamkills":0,"knifekills":0,"knifed":1,"suicides":0,"sips":31,"rounds":15,"active":true},{"id":"STEAM_0:1:34134896","name":"emil","team":"TERRORIST","kills":4,"deaths":7,"teamkills":0,"knifekills":2,"knifed":1,"suicides":0,"sips":30,"rounds":15,"active":true},{"id":"STEAM_0:1:14846448","name":"Thue","team":"UNASSIGNED","kills":0,"deaths":0,"teamkills":0,"knifekills":0,"knifed":0,"suicides":0,"sips":0,"rounds":0,"active":false}]}