{"startTime":1660076506008,"endTime":1660074811299,"scores":[{"id":"STEAM_0:1:11611559","name":"BOBKASMOPS | alstrup","team":"TERRORIST","kills":24,"deaths":7,"teamkills":0,"knifekills":0,"knifed":0,"suicides":0,"sips":73,"rounds":18,"active":false},{"id":"STEAM_0:0:29158958","name":"SJAJAMEPPE | Bernth","team":"CT","kills":12,"deaths":16,"teamkills":0,"knifekills":2,"knifed":0,"suicides":0,"sips":58,"rounds":18,"active":false},{"id":"STEAM_0:1:34134896","name":"det skui ad laif | emiL","team":"TERRORIST","kills":13,"deaths":12,"teamkills":0,"knifekills":2,"knifed":0,"suicides":0,"sips":56,"rounds":18,"active":false},{"id":"STEAM_0:0:1936508","name":"Heinz","team":"CT","kills":12,"deaths":11,"teamkills":1,"knifekills":0,"knifed":2,"suicides":0,"sips":54,"rounds":18,"active":false},{"id":"STEAM_0:0:161232090","name":"BOBKACARO","team":"CT","kills":10,"deaths":16,"teamkills":0,"knifekills":0,"knifed":1,"suicides":0,"sips":54,"rounds":18,"active":false},{"id":"STEAM_0:1:39235412","name":"CHRISToffer|| chris","team":"TERRORIST","kills":11,"deaths":8,"teamkills":0,"knifekills":1,"knifed":2,"suicides":0,"sips":48,"rounds":18,"active":false},{"id":"STEAM_0:1:156056572","name":"stonks | mai","team":"TERRORIST","kills":8,"deaths":11,"teamkills":0,"knifekills":0,"knifed":0,"suicides":0,"sips":45,"rounds":18,"active":false},{"id":"STEAM_0:1:575443358","name":"no bobka 2day | Jeameppe","team":"CT","kills":5,"deaths":14,"teamkills":0,"knifekills":0,"knifed":0,"suicides":0,"sips":42,"rounds":18,"active":false}]}