{"startTime":1666042952371,"endTime":1666042225846,"scores":[{"id":"STEAM_0:0:32762533","name":"Øl | jÆBBØH","team":"CT","kills":20,"deaths":7,"teamkills":0,"knifekills":0,"knifed":0,"suicides":0,"sips":67,"rounds":20,"active":true},{"id":"STEAM_0:1:13218758","name":"Camouflage | Mikki","team":"TERRORIST","kills":7,"deaths":15,"teamkills":0,"knifekills":0,"knifed":0,"suicides":0,"sips":49,"rounds":20,"active":true},{"id":"STEAM_0:0:1936508","name":"Heinz","team":"TERRORIST","kills":6,"deaths":16,"teamkills":0,"knifekills":0,"knifed":1,"suicides":0,"sips":48,"rounds":20,"active":true},{"id":"STEAM_0:1:34134896","name":"f10 for fun | emil","team":"CT","kills":11,"deaths":6,"teamkills":0,"knifekills":1,"knifed":0,"suicides":0,"sips":48,"rounds":20,"active":true}]}