{"startTime":1723228213174,"endTime":1723228201767,"scores":[{"id":"STEAM_0:1:11318024","name":"Mark | Bob","team":"TERRORIST","kills":4,"deaths":0,"teamkills":0,"knifekills":0,"knifed":0,"suicides":0,"sips":10,"rounds":2,"active":false},{"id":"STEAM_0:0:161232090","name":"Gangbanang | CARO","team":"CT","kills":1,"deaths":2,"teamkills":0,"knifekills":0,"knifed":0,"suicides":0,"sips":5,"rounds":1,"active":false},{"id":"STEAM_0:1:11611559","name":"Current Year Gang | Alstrup","team":"CT","kills":0,"deaths":2,"teamkills":0,"knifekills":0,"knifed":0,"suicides":0,"sips":4,"rounds":2,"active":false},{"id":"STEAM_0:1:575443358","name":"JEAMEPPE","team":"TERRORIST","kills":0,"deaths":1,"teamkills":0,"knifekills":0,"knifed":0,"suicides":0,"sips":3,"rounds":2,"active":false},{"id":"STEAM_0:0:1936508","name":"NeanderLANere|Heinz","team":"UNASSIGNED","kills":0,"deaths":0,"teamkills":0,"knifekills":0,"knifed":0,"suicides":0,"sips":0,"rounds":0,"active":false}]}