{"startTime":1729287470462,"endTime":1729286362516,"scores":[{"id":"STEAM_0:0:21651069","name":"mARKpLeT UUUWHHIIII","team":"TERRORIST","kills":40,"deaths":13,"teamkills":2,"knifekills":1,"knifed":1,"suicides":0,"sips":118,"rounds":17,"active":true},{"id":"STEAM_0:1:11611559","name":"NOOT NOOT | ALSTRUP","team":"CT","kills":24,"deaths":13,"teamkills":0,"knifekills":0,"knifed":0,"suicides":1,"sips":87,"rounds":17,"active":true},{"id":"STEAM_0:1:575443358","name":"NOOT NOOT | JEAMEPPE","team":"CT","kills":15,"deaths":14,"teamkills":0,"knifekills":2,"knifed":0,"suicides":2,"sips":79,"rounds":17,"active":true},{"id":"STEAM_0:0:29158958","name":"Mikki er boomer | bernth","team":"CT","kills":12,"deaths":16,"teamkills":0,"knifekills":1,"knifed":0,"suicides":2,"sips":75,"rounds":17,"active":true},{"id":"STEAM_0:1:14846448","name":"Thue","team":"CT","kills":11,"deaths":8,"teamkills":2,"knifekills":0,"knifed":0,"suicides":0,"sips":64,"rounds":16,"active":true},{"id":"STEAM_0:0:161232090","name":"UwU | CARO","team":"TERRORIST","kills":13,"deaths":13,"teamkills":1,"knifekills":1,"knifed":0,"suicides":0,"sips":64,"rounds":17,"active":true},{"id":"STEAM_0:1:94067284","name":"Nicklas | help me","team":"CT","kills":12,"deaths":11,"teamkills":0,"knifekills":1,"knifed":0,"suicides":1,"sips":61,"rounds":17,"active":true},{"id":"STEAM_0:1:156056572","name":"stonks | mai","team":"TERRORIST","kills":15,"deaths":14,"teamkills":0,"knifekills":0,"knifed":1,"suicides":0,"sips":61,"rounds":17,"active":true},{"id":"STEAM_0:0:1936508","name":"Heinz","team":"CT","kills":13,"deaths":13,"teamkills":0,"knifekills":0,"knifed":0,"suicides":0,"sips":56,"rounds":17,"active":true},{"id":"STEAM_0:0:424011233","name":"Noot Noot MF | Maria","team":"TERRORIST","kills":8,"deaths":13,"teamkills":0,"knifekills":0,"knifed":3,"suicides":1,"sips":55,"rounds":17,"active":true},{"id":"STEAM_0:1:11318024","name":"My precious!|Bob","team":"CT","kills":10,"deaths":14,"teamkills":0,"knifekills":3,"knifed":0,"suicides":0,"sips":51,"rounds":17,"active":true},{"id":"STEAM_0:0:32762533","name":"Kuglelejet | jÆBBØH","team":"TERRORIST","kills":10,"deaths":14,"teamkills":0,"knifekills":0,"knifed":0,"suicides":0,"sips":51,"rounds":17,"active":true},{"id":"STEAM_0:1:13218758","name":"Gammel og Grim | Mikki","team":"CT","kills":1,"deaths":11,"teamkills":0,"knifekills":0,"knifed":1,"suicides":2,"sips":48,"rounds":17,"active":true},{"id":"STEAM_0:1:31416024","name":"sSIMONNNxx","team":"TERRORIST","kills":8,"deaths":14,"teamkills":0,"knifekills":0,"knifed":2,"suicides":0,"sips":47,"rounds":17,"active":true},{"id":"STEAM_0:1:34134896","name":"tilløh, mikgi, storre?|e.m.i.l","team":"CT","kills":8,"deaths":11,"teamkills":0,"knifekills":5,"knifed":1,"suicides":0,"sips":44,"rounds":17,"active":true},{"id":"STEAM_0:1:9958215","name":"сука блять | Niels","team":"TERRORIST","kills":6,"deaths":13,"teamkills":0,"knifekills":0,"knifed":4,"suicides":0,"sips":42,"rounds":17,"active":true},{"id":"STEAM_0:1:68620002","name":"Kastrup | laura","team":"TERRORIST","kills":4,"deaths":14,"teamkills":0,"knifekills":0,"knifed":1,"suicides":0,"sips":39,"rounds":17,"active":true},{"id":"STEAM_0:1:39235412","name":"Cognitohazard | Chris","team":"UNASSIGNED","kills":0,"deaths":0,"teamkills":0,"knifekills":0,"knifed":0,"suicides":0,"sips":0,"rounds":0,"active":false}]}