{"startTime":1744923425082,"endTime":1744922419026,"scores":[{"id":"STEAM_0:1:31416024","name":"Fly-bygger | SIMON","team":"CT","kills":9,"deaths":13,"teamkills":4,"knifekills":2,"knifed":1,"suicides":0,"sips":80,"rounds":14,"active":true},{"id":"STEAM_0:1:94067284","name":"Ølbaronen | Nicklas","team":"CT","kills":22,"deaths":8,"teamkills":0,"knifekills":0,"knifed":1,"suicides":0,"sips":66,"rounds":14,"active":true},{"id":"STEAM_0:0:46546093","name":"AN3RK1S7| aMiN","team":"TERRORIST","kills":20,"deaths":9,"teamkills":0,"knifekills":10,"knifed":0,"suicides":0,"sips":63,"rounds":14,"active":true},{"id":"STEAM_0:0:21651069","name":"mARK | tALENTLØS","team":"TERRORIST","kills":19,"deaths":8,"teamkills":1,"knifekills":0,"knifed":0,"suicides":0,"sips":61,"rounds":14,"active":true},{"id":"STEAM_0:1:11611559","name":"1TK0S | Alstrup","team":"CT","kills":16,"deaths":9,"teamkills":0,"knifekills":0,"knifed":0,"suicides":0,"sips":55,"rounds":14,"active":true},{"id":"STEAM_0:0:1936508","name":"Heinz","team":"TERRORIST","kills":13,"deaths":11,"teamkills":0,"knifekills":0,"knifed":0,"suicides":0,"sips":51,"rounds":14,"active":true},{"id":"STEAM_0:0:424011233","name":"Noot Noot MF | Maria","team":"CT","kills":8,"deaths":11,"teamkills":2,"knifekills":0,"knifed":2,"suicides":0,"sips":50,"rounds":14,"active":true},{"id":"STEAM_0:0:161232090","name":"CARO >:(","team":"TERRORIST","kills":13,"deaths":9,"teamkills":0,"knifekills":0,"knifed":1,"suicides":0,"sips":49,"rounds":14,"active":true},{"id":"STEAM_0:1:74714937","name":"flystyrter | thor","team":"CT","kills":6,"deaths":7,"teamkills":2,"knifekills":0,"knifed":0,"suicides":0,"sips":48,"rounds":14,"active":true},{"id":"STEAM_0:0:29158958","name":"1TK0S | Bernth","team":"CT","kills":9,"deaths":11,"teamkills":0,"knifekills":0,"knifed":2,"suicides":0,"sips":43,"rounds":14,"active":true},{"id":"STEAM_0:0:57382995","name":"Helene Kirkeby","team":"CT","kills":8,"deaths":11,"teamkills":0,"knifekills":0,"knifed":1,"suicides":0,"sips":41,"rounds":14,"active":true},{"id":"STEAM_0:1:156056572","name":"stonks tk? | mai","team":"CT","kills":6,"deaths":10,"teamkills":0,"knifekills":0,"knifed":3,"suicides":0,"sips":36,"rounds":14,"active":true},{"id":"STEAM_0:1:39235412","name":"Forlod Hobro For dette?|Chris","team":"CT","kills":6,"deaths":8,"teamkills":0,"knifekills":2,"knifed":0,"suicides":0,"sips":34,"rounds":14,"active":true},{"id":"STEAM_0:1:9958215","name":"Swagolas | Niels","team":"TERRORIST","kills":5,"deaths":9,"teamkills":0,"knifekills":0,"knifed":1,"suicides":0,"sips":33,"rounds":14,"active":true},{"id":"STEAM_0:1:48431488","name":"Farmand | Jonas","team":"TERRORIST","kills":4,"deaths":10,"teamkills":0,"knifekills":0,"knifed":1,"suicides":0,"sips":32,"rounds":14,"active":true},{"id":"STEAM_0:1:68620002","name":"Ben Dover | laura","team":"TERRORIST","kills":4,"deaths":8,"teamkills":0,"knifekills":0,"knifed":0,"suicides":0,"sips":30,"rounds":14,"active":true},{"id":"STEAM_0:1:34134896","name":"det er sku da gutterne @ emil","team":"TERRORIST","kills":2,"deaths":10,"teamkills":0,"knifekills":0,"knifed":0,"suicides":0,"sips":28,"rounds":14,"active":true},{"id":"STEAM_0:1:13218758","name":"6TK0S | Mikki","team":"TERRORIST","kills":1,"deaths":9,"teamkills":0,"knifekills":0,"knifed":1,"suicides":0,"sips":25,"rounds":14,"active":true}]}